psweep/__init__.py
psweep/cli.py
psweep/psweep.py
psweep-0.15.0.data/scripts/psweep-db2json
psweep-0.15.0.data/scripts/psweep-db2table
psweep-0.15.0.data/scripts/psweep-pull
psweep-0.15.0.data/scripts/psweep-push
psweep-0.15.0.dist-info/licenses/LICENSE
psweep-0.15.0.dist-info/METADATA
psweep-0.15.0.dist-info/WHEEL
psweep-0.15.0.dist-info/entry_points.txt
psweep-0.15.0.dist-info/top_level.txt
psweep-0.15.0.dist-info/RECORD
