Metadata-Version: 2.4
Name: psweep
Version: 0.15.0
Summary: loop like a pro, make parameter studies fun
Author-email: Steve Schmerler <git@elcorto.com>
License: Copyright (c) 2025, Steve Schmerler <git@elcorto.com>
Project-URL: Homepage, https://github.com/elcorto/psweep
Project-URL: Documentation, https://elcorto.github.io/psweep
Project-URL: Source, https://github.com/elcorto/psweep.git
Project-URL: Issues, https://github.com/elcorto/psweep/issues
Keywords: computational-experiment,parameter-sweep,parameter-scan,parameter-study,pandas,database
Requires-Python: >=3.10
License-File: LICENSE
Requires-Dist: numpy
Requires-Dist: pandas>=0.19.2
Requires-Dist: pyyaml
Requires-Dist: joblib
Requires-Dist: Jinja2
Requires-Dist: docopt
Requires-Dist: tabulate>=0.8.2
Provides-Extra: test
Requires-Dist: pytest; extra == "test"
Requires-Dist: pytest-xdist; extra == "test"
Provides-Extra: dev
Requires-Dist: pre-commit; extra == "dev"
Provides-Extra: dask
Requires-Dist: dask; extra == "dask"
Requires-Dist: dask-jobqueue; extra == "dask"
Requires-Dist: distributed; extra == "dask"
Dynamic: license-file
